mepe/__init__.py
mepe/display.py
mepe/exceptions.py
mepe/main.py
mepe/scrape.py
mepe-0.1.5.dist-info/entry_points.txt
mepe-0.1.5.dist-info/LICENSE
mepe-0.1.5.dist-info/WHEEL
mepe-0.1.5.dist-info/METADATA
mepe-0.1.5.dist-info/RECORD
